[
    {
        "name": "FL Simulation",
        "protocol": "sftp",
        "port": 22,
        "privateKeyPath": "/Users/danski/.ssh/id_rsa",
        "uploadOnSave": true,
        "profiles": {
            "gpu1": {
                "host": "gpu-1",
                "remotePath": "/home/gpu-1/kiedanski/fl-edge-simulation"
            },
            "fast": {
                "host": "fast",
                "remotePath": "/home/exx/kiedanski/fl-edge-simulation"
            }
        },
        "defaultProfile": "fast",
        "ignore": [
            ".vscode",
            "lightning_logs",
            "__pycache__"
        ]
    }
]